PDFVisor/PDFViewr.py
PDFVisor/__init__.py
PDFVisor/funcsVisorPDF.py
PDFVisor/times.ttf
PDFVisor/img/avanceDeshabilitado.png
PDFVisor/img/avanceHighlight.png
PDFVisor/img/avanceHighlightPressed.png
PDFVisor/img/avanceNormal.png
PDFVisor/img/retroDeshabilitado.png
PDFVisor/img/retroHighlight.png
PDFVisor/img/retroHighlightPressed.png
PDFVisor/img/retroNormal.png
PDFVisor-0.1.5.dist-info/LICENSE.rst
PDFVisor-0.1.5.dist-info/METADATA
PDFVisor-0.1.5.dist-info/WHEEL
PDFVisor-0.1.5.dist-info/top_level.txt
PDFVisor-0.1.5.dist-info/RECORD
