Metadata-Version: 2.1
Name: PDFVisor
Version: 0.1.5
Summary: Recurso para moverse por documentos PDF
Author: Antonio San Román
Author-email: asanro46@gmail.com
License: MIT
Requires-Python: >=3.4
License-File: LICENSE.rst
Requires-Dist: PyPDF2
Requires-Dist: Pillow
Requires-Dist: numpy
Requires-Dist: PyMuPDF
Requires-Dist: opencv-contrib-python
